aiodesa/__init__.py
aiodesa/database.py
aiodesa/utils/table.py
aiodesa/utils/util_types.py
aiodesa-0.2.0.dist-info/LICENSE
aiodesa-0.2.0.dist-info/METADATA
aiodesa-0.2.0.dist-info/WHEEL
aiodesa-0.2.0.dist-info/RECORD
