Metadata-Version: 2.1
Name: aiodesa
Version: 0.2.0
Summary: AIODesa offers a straightforward and 100% Python interface for managing asynchronous data access. By leveraging Python's built-ins and standard library, it seamlessly wraps around AioSqlite, providing a hassle-free experience. With AIODesa, you can define, generate, and commit data effortlessly, thanks to shared objects for tables and records.
Author: sockheadrps
Author-email: r.p.skiles@gmail.com
Requires-Python: >=3.11,<4.0
Classifier: Programming Language :: Python :: 3
Classifier: Programming Language :: Python :: 3.11
Requires-Dist: aiohttp (>=3.9.1,<4.0.0)
Requires-Dist: aiosqlite (>=0.19.0,<0.20.0)
Requires-Dist: pre-commit (>=3.6.0,<4.0.0)
